Metadata-Version: 1.0
Name: rdel-distributions
Version: 1.1
Summary: Gaussian and binomial distributions
Home-page: UNKNOWN
Author: Ronda Lunn
Author-email: ronda@rondalunn.com
License: UNKNOWN
Platform: UNKNOWN
